modbuslink/__init__.py
modbuslink/client/__init__.py
modbuslink/client/async_client.py
modbuslink/client/sync_client.py
modbuslink/common/__init__.py
modbuslink/common/exceptions.py
modbuslink/common/language.py
modbuslink/server/__init__.py
modbuslink/server/async_ascii_server.py
modbuslink/server/async_base_server.py
modbuslink/server/async_rtu_server.py
modbuslink/server/async_tcp_server.py
modbuslink/server/data_store.py
modbuslink/transport/__init__.py
modbuslink/transport/ascii.py
modbuslink/transport/async_ascii.py
modbuslink/transport/async_base.py
modbuslink/transport/async_rtu.py
modbuslink/transport/async_tcp.py
modbuslink/transport/base.py
modbuslink/transport/rtu.py
modbuslink/transport/tcp.py
modbuslink/utils/__init__.py
modbuslink/utils/coder.py
modbuslink/utils/crc.py
modbuslink/utils/logging.py
modbuslink-1.3.4.dist-info/licenses/LICENSE.txt
modbuslink-1.3.4.dist-info/METADATA
modbuslink-1.3.4.dist-info/WHEEL
modbuslink-1.3.4.dist-info/top_level.txt
modbuslink-1.3.4.dist-info/RECORD
