Metadata-Version: 2.4
Name: modbuslink
Version: 1.3.4
Summary: 现代化、功能强大、开发者友好且高度可扩展的Python Modbus库 | Modern, powerful, developer-friendly and highly scalable Python Modbus library
Author-email: Miraitowa-la <2056978412@qq.com>
License: MIT
Project-URL: Homepage, https://github.com/Miraitowa-la/ModbusLink
Project-URL: Repository, https://github.com/Miraitowa-la/ModbusLink
Project-URL: Issues, https://github.com/Miraitowa-la/ModbusLink/issues
Keywords: modbus,industrial,automation,communication,protocol,tcp,rtu,ascii,serial,plc,scada,iot
Classifier: Development Status :: 3 - Alpha
Classifier: Intended Audience :: Developers
Classifier: License :: OSI Approved :: MIT License
Classifier: Operating System :: OS Independent
Classifier: Programming Language :: Python :: 3
Classifier: Programming Language :: Python :: 3.9
Classifier: Programming Language :: Python :: 3.10
Classifier: Programming Language :: Python :: 3.11
Classifier: Programming Language :: Python :: 3.12
Classifier: Topic :: Software Development :: Libraries :: Python Modules
Classifier: Topic :: System :: Hardware
Classifier: Topic :: Communications
Requires-Python: >=3.9
License-File: LICENSE.txt
Requires-Dist: pyserial>=3.5
Requires-Dist: pyserial-asyncio>=0.6
Requires-Dist: typing_extensions>=4.0.0
Provides-Extra: dev
Requires-Dist: pytest>=7.0; extra == "dev"
Requires-Dist: pytest-mock>=3.0; extra == "dev"
Requires-Dist: black>=22.0; extra == "dev"
Requires-Dist: ruff>=0.1.0; extra == "dev"
Requires-Dist: mypy>=1.0; extra == "dev"
Dynamic: license-file
